jupyter_rtc/__init__.py
jupyter_rtc/_version.py
jupyter_rtc/handlers.py
jupyter_rtc/tests/__init__.py
jupyter_rtc/tests/test_handlers.py
jupyter_rtc-0.0.3.data/data/etc/jupyter/jupyter_notebook_config.d/jupyter_rtc.json
jupyter_rtc-0.0.3.data/data/etc/jupyter/jupyter_server_config.d/jupyter_rtc.json
jupyter_rtc-0.0.3.data/data/share/jupyter/labextensions/@datalayer/jupyter-rtc/build_log.json
jupyter_rtc-0.0.3.data/data/share/jupyter/labextensions/@datalayer/jupyter-rtc/package.json
jupyter_rtc-0.0.3.data/data/share/jupyter/labextensions/@datalayer/jupyter-rtc/schemas/@datalayer/jupyter-rtc/package.json.orig
jupyter_rtc-0.0.3.data/data/share/jupyter/labextensions/@datalayer/jupyter-rtc/schemas/@datalayer/jupyter-rtc/plugin.json
jupyter_rtc-0.0.3.data/data/share/jupyter/labextensions/@datalayer/jupyter-rtc/static/design_icons_lib_index_js.781963b06134c0b4e39a.js
jupyter_rtc-0.0.3.data/data/share/jupyter/labextensions/@datalayer/jupyter-rtc/static/design_icons_lib_index_js.781963b06134c0b4e39a.js.map
jupyter_rtc-0.0.3.data/data/share/jupyter/labextensions/@datalayer/jupyter-rtc/static/lib_index_js.85f243819a354a405ea8.js
jupyter_rtc-0.0.3.data/data/share/jupyter/labextensions/@datalayer/jupyter-rtc/static/lib_index_js.85f243819a354a405ea8.js.map
jupyter_rtc-0.0.3.data/data/share/jupyter/labextensions/@datalayer/jupyter-rtc/static/node_modules_object-assign_index_js.7cd9a741ea71f6df4219.js
jupyter_rtc-0.0.3.data/data/share/jupyter/labextensions/@datalayer/jupyter-rtc/static/node_modules_object-assign_index_js.7cd9a741ea71f6df4219.js.map
jupyter_rtc-0.0.3.data/data/share/jupyter/labextensions/@datalayer/jupyter-rtc/static/remoteEntry.88312cb9ec7bff4532b4.js
jupyter_rtc-0.0.3.data/data/share/jupyter/labextensions/@datalayer/jupyter-rtc/static/remoteEntry.88312cb9ec7bff4532b4.js.map
jupyter_rtc-0.0.3.data/data/share/jupyter/labextensions/@datalayer/jupyter-rtc/static/style.js
jupyter_rtc-0.0.3.dist-info/METADATA
jupyter_rtc-0.0.3.dist-info/WHEEL
jupyter_rtc-0.0.3.dist-info/licenses/LICENSE
jupyter_rtc-0.0.3.dist-info/RECORD
